{
  "forge:conditions": [
    {
      "type": "forge:mod_loaded",
      "modid": "endersdelight"
    }
  ],
  "type": "minecraft:crafting_shapeless",
  "ingredients": [
    {
      "item": "croptopia:cooking_pot"
    },
    {
      "item": "endersdelight:shulker_mollusk"
    },
    {
      "item": "minecraft:chorus_fruit"
    },
    {
      "tag": "forge:rice"
    },
    {
      "tag": "forge:vegetables/tomato"
    },
    {
      "item": "minecraft:brown_mushroom"
    },
    {
      "item": "minecraft:shulker_shell"
    }
  ],
  "result": {
    "item": "endersdelight:stuffed_shulker"
  }
}